{"chunk_definitions":[{"row":119,"row_count":1,"visible":true,"expansion_state":0,"options":{"engine":"r","label":"setup","include":false},"document_id":"AD6F95B2","chunk_id":"csetup_chunk","chunk_label":"setup"},{"row":141,"row_count":1,"visible":true,"expansion_state":0,"options":{"engine":"r","label":"unnamed-chunk-5"},"document_id":"AD6F95B2","chunk_id":"ceiewpalrjfnu","chunk_label":"unnamed-chunk-3"},{"row":163,"row_count":1,"visible":true,"expansion_state":0,"options":{"engine":"r","label":"unnamed-chunk-113"},"document_id":"AD6F95B2","chunk_id":"cs4ar6i2k4p8k","chunk_label":"unnamed-chunk-4"},{"row":367,"row_count":1,"visible":true,"expansion_state":0,"options":{"engine":"r","warning":false,"label":"unnamed-chunk-74"},"document_id":"AD6F95B2","chunk_id":"ccrtrzcryr3zr","chunk_label":"unnamed-chunk-5"},{"row":391,"row_count":1,"visible":true,"expansion_state":0,"options":{"engine":"r","label":"unnamed-chunk-4"},"document_id":"AD6F95B2","chunk_id":"cv681tnfpfwoq","chunk_label":"unnamed-chunk-7"},{"row":438,"row_count":1,"visible":true,"expansion_state":0,"options":{"engine":"r","label":"unnamed-chunk-53"},"document_id":"AD6F95B2","chunk_id":"c1p2as6jzddn5","chunk_label":"unnamed-chunk-8"},{"row":517,"row_count":1,"visible":true,"expansion_state":0,"options":{"engine":"r","warning":false,"label":"unnamed-chunk-12"},"document_id":"AD6F95B2","chunk_id":"c4wb5a8853v0p","chunk_label":"unnamed-chunk-9"},{"row":552,"row_count":1,"visible":true,"expansion_state":0,"options":{"engine":"r","label":"unnamed-chunk-2"},"document_id":"AD6F95B2","chunk_id":"crxokfq5wxtqp","chunk_label":"unnamed-chunk-11"},{"row":567,"row_count":1,"visible":true,"expansion_state":0,"options":{"engine":"r","label":"unnamed-chunk-55"},"document_id":"AD6F95B2","chunk_id":"c3q4nbu7iyik0","chunk_label":"unnamed-chunk-12"},{"row":578,"row_count":1,"visible":true,"expansion_state":0,"options":{"engine":"r","label":"unnamed-chunk-58"},"document_id":"AD6F95B2","chunk_id":"ctk7b1h0mb39t","chunk_label":"unnamed-chunk-13"},{"row":594,"row_count":1,"visible":true,"expansion_state":0,"options":{"engine":"r","label":"unnamed-chunk-2"},"document_id":"AD6F95B2","chunk_id":"cp6krklgqhjvd","chunk_label":"unnamed-chunk-14"},{"row":604,"row_count":1,"visible":true,"expansion_state":0,"options":{"engine":"r","label":"unnamed-chunk-4"},"document_id":"AD6F95B2","chunk_id":"cry2a2pwo96bx","chunk_label":"unnamed-chunk-15"},{"row":633,"row_count":1,"visible":true,"expansion_state":0,"options":{"engine":"r","label":"unnamed-chunk-23"},"document_id":"AD6F95B2","chunk_id":"cb2wj0fbaeo8u","chunk_label":"unnamed-chunk-17"},{"row":645,"row_count":1,"visible":true,"expansion_state":0,"options":{"engine":"r","label":"unnamed-chunk-9"},"document_id":"AD6F95B2","chunk_id":"ct0g2i4iux92a","chunk_label":"unnamed-chunk-18"},{"row":662,"row_count":1,"visible":true,"expansion_state":0,"options":{"engine":"r","label":"unnamed-chunk-12"},"document_id":"AD6F95B2","chunk_id":"coutdf7eklnfx","chunk_label":"unnamed-chunk-19"},{"row":676,"row_count":1,"visible":true,"expansion_state":0,"options":{"engine":"r","label":"unnamed-chunk-15"},"document_id":"AD6F95B2","chunk_id":"cmjy7g7ucmi2n","chunk_label":"unnamed-chunk-20"},{"row":684,"row_count":1,"visible":true,"expansion_state":0,"options":{"engine":"r","label":"unnamed-chunk-13"},"document_id":"AD6F95B2","chunk_id":"cljbcm8vlxc8q","chunk_label":"unnamed-chunk-21"}],"doc_write_time":1680704653,"working_dir":null,"default_chunk_options":{"echo":false,"fig.width":9.0,"message":false,"warning":false}}